{
  "version": "5923",
  "id": "cold",
  "name": "Cold",
  "short_name": "Cold",
  "dna": {
    "belly": "1",
    "bellybutton": "1",
    "body": "1",
    "cheek": "3",
    "collar": "0",
    "ear": "12",
    "eye": "2",
    "hair": "2",
    "head": "1",
    "horn": "2",
    "mouth": "6",
    "nose": "1",
    "tail": "4",
    "accessory": "0",
    "line_rgb": "6c4331",
    "body_rgb": "23a2e3",
    "belly_rgb": "35e1e0",
    "cloth_rgb": "415a73",
    "glass_rgb": "bf3a3a",
    "plastic_rgb": "3d3c3b",
    "hair_rgb": "ffffff",
    "horn_rgb": "fde9e7",
    "eye_rgb_0": "415a73",
    "eye_rgb_1": "c8cbd6"
  },
  "chat_theme": {
    "accent_scale": 4.6,
    "accent_swapped": true,
    "accent_texture": 13,
    "color": "23a2e3",
    "dark": true
  }
}