{
  "version": "5c84",
  "name": "Basic Techniques",
  "finish_condition": {
    "type": "score",
    "value": 100
  },
  "lose_condition": [
    "top_out 999999"
  ],
  "other": [
    "after_tutorial",
    "start_level tutorial/basics_0"
  ],
  "piece_types": [
    "start_piece_q",
    "start_piece_l"
  ],
  "rank": [
    "duration 90",
    "rank_criteria top=3599",
    "skip_results",
    "unranked"
  ],
  "tiles": {
    "start": [
      {
        "pos": "0 17",
        "tile": "1 10 3"
      },
      {
        "pos": "1 17",
        "tile": "1 14 3"
      },
      {
        "pos": "2 17",
        "tile": "1 6 3"
      },
      {
        "pos": "4 17",
        "tile": "2 0 0"
      },
      {
        "pos": "5 17",
        "tile": "1 10 5"
      },
      {
        "pos": "6 17",
        "tile": "1 14 5"
      },
      {
        "pos": "7 17",
        "tile": "1 14 5"
      },
      {
        "pos": "8 17",
        "tile": "1 6 5"
      },
      {
        "pos": "0 18",
        "tile": "1 11 3"
      },
      {
        "pos": "1 18",
        "tile": "1 15 3"
      },
      {
        "pos": "2 18",
        "tile": "1 7 3"
      },
      {
        "pos": "5 18",
        "tile": "1 11 5"
      },
      {
        "pos": "6 18",
        "tile": "1 15 5"
      },
      {
        "pos": "7 18",
        "tile": "1 15 5"
      },
      {
        "pos": "8 18",
        "tile": "1 7 5"
      },
      {
        "pos": "0 19",
        "tile": "1 9 3"
      },
      {
        "pos": "1 19",
        "tile": "1 13 3"
      },
      {
        "pos": "2 19",
        "tile": "1 5 3"
      },
      {
        "pos": "5 19",
        "tile": "1 9 5"
      },
      {
        "pos": "6 19",
        "tile": "1 13 5"
      },
      {
        "pos": "7 19",
        "tile": "1 13 5"
      },
      {
        "pos": "8 19",
        "tile": "1 5 5"
      }
    ]
  }
}