{
  "version": "5c84",
  "start_speed": "T",
  "blocks_during": [
    "top_out_effect refresh"
  ],
  "finish_condition": {
    "type": "pieces",
    "value": 1
  },
  "lose_condition": [
    "top_out 999999"
  ],
  "other": [
    "start_level tutorial/spins_0",
    "tutorial"
  ],
  "piece_types": [
    "piece_u"
  ],
  "rank": [
    "duration 150",
    "rank_criteria top=1",
    "skip_results",
    "unranked"
  ],
  "tiles": {
    "start": [
      {
        "pos": "5 10",
        "tile": "2 15 3"
      },
      {
        "pos": "8 10",
        "tile": "2 8 0"
      },
      {
        "pos": "2 11",
        "tile": "2 12 0"
      },
      {
        "pos": "6 11",
        "tile": "2 0 2"
      },
      {
        "pos": "8 11",
        "tile": "2 5 3"
      },
      {
        "pos": "1 12",
        "tile": "2 13 0"
      },
      {
        "pos": "3 12",
        "tile": "2 15 1"
      },
      {
        "pos": "8 12",
        "tile": "2 11 1"
      },
      {
        "pos": "5 13",
        "tile": "2 10 1"
      },
      {
        "pos": "7 13",
        "tile": "2 3 3"
      },
      {
        "pos": "8 13",
        "tile": "2 6 1"
      },
      {
        "pos": "1 14",
        "tile": "2 11 1"
      },
      {
        "pos": "3 14",
        "tile": "2 4 3"
      },
      {
        "pos": "4 14",
        "tile": "2 13 2"
      },
      {
        "pos": "5 14",
        "tile": "2 9 1"
      },
      {
        "pos": "7 14",
        "tile": "2 9 0"
      },
      {
        "pos": "8 14",
        "tile": "2 14 0"
      },
      {
        "pos": "8 15",
        "tile": "0 2 2"
      },
      {
        "pos": "1 16",
        "tile": "2 17 3"
      },
      {
        "pos": "3 16",
        "tile": "2 14 1"
      },
      {
        "pos": "4 16",
        "tile": "2 11 3"
      },
      {
        "pos": "5 16",
        "tile": "2 3 1"
      },
      {
        "pos": "7 16",
        "tile": "0 8 2"
      },
      {
        "pos": "8 16",
        "tile": "0 7 2"
      },
      {
        "pos": "0 17",
        "tile": "2 2 2"
      },
      {
        "pos": "8 17",
        "tile": "0 1 2"
      },
      {
        "pos": "3 18",
        "tile": "2 2 1"
      },
      {
        "pos": "5 18",
        "tile": "2 10 0"
      },
      {
        "pos": "2 19",
        "tile": "2 9 2"
      },
      {
        "pos": "6 19",
        "tile": "2 13 1"
      }
    ]
  }
}