{
  "version": "4c5c",
  "name": "It Takes Two",
  "description": "What takes two? ...Oh please no, not that...",
  "start_speed": "A1",
  "blocks_during": [
    "clear_on_top_out",
    "filled_line_clear_max 1",
    "filled_line_clear_min 2",
    "filled_line_clear_order lowest"
  ],
  "finish_condition": {
    "type": "pieces",
    "value": 165
  },
  "rank": [
    "box_factor 0.96",
    "combo_factor 0.58",
    "extra_seconds_per_piece 0.39"
  ],
  "tiles": {
    "start": [
      {
        "pos": "0 18",
        "tile": "1 10 12"
      },
      {
        "pos": "1 18",
        "tile": "1 14 12"
      },
      {
        "pos": "2 18",
        "tile": "1 6 12"
      },
      {
        "pos": "6 18",
        "tile": "1 10 12"
      },
      {
        "pos": "7 18",
        "tile": "1 14 12"
      },
      {
        "pos": "8 18",
        "tile": "1 6 12"
      },
      {
        "pos": "0 19",
        "tile": "1 9 12"
      },
      {
        "pos": "1 19",
        "tile": "1 13 12"
      },
      {
        "pos": "2 19",
        "tile": "1 5 12"
      },
      {
        "pos": "3 19",
        "tile": "1 8 2"
      },
      {
        "pos": "4 19",
        "tile": "1 12 2"
      },
      {
        "pos": "5 19",
        "tile": "1 4 2"
      },
      {
        "pos": "6 19",
        "tile": "1 9 12"
      },
      {
        "pos": "7 19",
        "tile": "1 13 12"
      },
      {
        "pos": "8 19",
        "tile": "1 5 12"
      }
    ]
  }
}