{
  "version": "5c84",
  "name": "Secret Brownies",
  "description": "Secret brownies? Where? ...I must have them!",
  "blocks_during": [
    "pickup_type float_regen"
  ],
  "finish_condition": {
    "type": "lines",
    "value": 15
  },
  "icons": [
    "sneaky",
    "slow"
  ],
  "rank": [
    "duration 115",
    "rank_criteria top=1000 s-=135"
  ],
  "tiles": {
    "start": [
      {
        "pos": "7 16",
        "tile": "0 2 2"
      },
      {
        "pos": "6 17",
        "tile": "0 8 2"
      },
      {
        "pos": "7 17",
        "tile": "0 13 2"
      },
      {
        "pos": "8 17",
        "tile": "0 4 2",
        "pickup": "2"
      },
      {
        "pos": "6 18",
        "tile": "1 10 0"
      },
      {
        "pos": "7 18",
        "tile": "1 14 0",
        "pickup": "9"
      },
      {
        "pos": "8 18",
        "tile": "1 6 0"
      },
      {
        "pos": "6 19",
        "tile": "1 9 0",
        "pickup": "9"
      },
      {
        "pos": "7 19",
        "tile": "1 13 0",
        "pickup": "0"
      },
      {
        "pos": "8 19",
        "tile": "1 5 0",
        "pickup": "9"
      }
    ]
  }
}